Metadata-Version: 1.1
Name: urlunshort3
Version: 0.2
Summary: Take a URL, compare to known shortening services, and expand it. A python3 rewrite of https://pypi.org/project/urlunshort/
Home-page: https://github.com/user/reponame
Author: remotephone
Author-email: remotephone@gmail.com
License: BSD
Keywords: urlshorten,expand,security
Platform: UNKNOWN
Classifier: Development Status :: 3 - Alpha
Classifier: Intended Audience :: Information Technology
Classifier: Topic :: Internet :: WWW/HTTP
Classifier: License :: OSI Approved :: BSD License
Classifier: Programming Language :: Python :: 3.6
